<li840><data><celltemp>5.13845e1</celltemp><cellpres>1.00367e2</cellpres><co2>-1.26502e-4</co2><co2abs>-2.8164386e-3</co2abs><h2o>-1.59174e-1</h2o><h2oabs>3.1495094e-4</h2oabs><h2odewpoint>-2.73149e2</h2odewpoint><raw><co2>2967714</co2><co2ref>3375819</co2ref><h2o>1392716</h2o><h2oref>1750179</h2oref></raw><datetime>2017-01-19T16:02:57.057574</datetime></data><ack>true</ack></li840>
<li840><data><celltemp>5.13845e1</celltemp><cellpres>1.00323e2</cellpres><co2>-1.26499e-4</co2><co2abs>-2.8517246e-3</co2abs><h2o>-2.14723e-1</h2o><h2oabs>4.2712688e-4</h2oabs><h2odewpoint>-2.73149e2</h2odewpoint><raw><co2>2967696</co2><co2ref>3375835</co2ref><h2o>1392561</h2o><h2oref>1750091</h2oref></raw><datetime>2017-01-19T16:04:33.700576</datetime></data></li840>
<li840><data><celltemp>5.13845e1</celltemp><cellpres>1.00411e2</cellpres><co2>-1.26457e-4</co2><co2abs>-2.7610063e-3</co2abs><h2o>-9.48227e-1</h2o><h2oabs>2.0608901e-3</h2oabs><h2odewpoint>-2.73149e2</h2odewpoint><raw><co2>2966847</co2><co2ref>3375467</co2ref><h2o>1390243</h2o><h2oref>1750021</h2oref></raw><datetime>2017-01-19T16:04:46.522163</datetime></data></li840>
